deno_vm/__init__.py
deno_vm/__pkginfo__.py
deno_vm/vm-server/deno.json
deno_vm/vm-server/index.js
deno_vm-0.5.1.dist-info/LICENSE
deno_vm-0.5.1.dist-info/METADATA
deno_vm-0.5.1.dist-info/WHEEL
deno_vm-0.5.1.dist-info/top_level.txt
deno_vm-0.5.1.dist-info/RECORD
