Metadata-Version: 2.1
Name: deno_vm
Version: 0.5.1
Summary: A binding to Deno + worker-vm, helps you execute JavaScript safely.
Home-page: https://github.com/eight04/deno_vm
Author: eight
Author-email: eight04@gmail.com
License: MIT
Keywords: deno,js,sandbox,execute,javascript
Platform: UNKNOWN
Classifier: Development Status :: 4 - Beta
Classifier: Environment :: Console
Classifier: Environment :: Win32 (MS Windows)
Classifier: Intended Audience :: Developers
Classifier: License :: OSI Approved :: MIT License
Classifier: Natural Language :: Chinese (Traditional)
Classifier: Operating System :: Microsoft :: Windows :: Windows 10
Classifier: Programming Language :: Python :: 3.10
Classifier: Programming Language :: JavaScript
Classifier: Topic :: Software Development :: Libraries
License-File: LICENSE
